{"swagger":"2.0","info":{"title":"eventory: ITイベント収集アプリ","description":"ITイベント情報集アプリAPI ","license":{"name":"MIT","url":"https://github.com/tikasan/eventory/blob/master/LICENSE"},"version":""},"host":"localhost:8080","schemes":["http"],"consumes":["application/json","application/xml","application/gob","application/x-gob"],"produces":["application/json","application/xml","application/gob","application/x-gob"],"paths":{"/api/v2/event":{"get":{"tags":["event"],"summary":"list event","description":"イベント情報取得(クライントはこの処理の実行した時間を保持する)","operationId":"event#list","produces":["application/vnd.goa.error","application/vnd.event+json; type=collection"],"parameters":[{"name":"updated_at","in":"query","description":"クライアントが最後にイベントを取得した時間(格納していない場合は空文字で処理します)","required":false,"type":"string","default":""}],"responses":{"200":{"description":"OK","schema":{"$ref":"#/definitions/EventCollection"}},"400":{"description":"Bad Request","schema":{"$ref":"#/definitions/error"}}},"schemes":["http"]}},"/api/v2/genre":{"get":{"tags":["genre"],"summary":"list genre","description":"all genre get","operationId":"genre#list","produces":["application/vnd.goa.error","application/vnd.genre+json; type=collection"],"parameters":[{"name":"keyword","in":"query","description":"ジャンル名検索に使うキーワード(0~30文字)","required":false,"type":"string","default":"","maxLength":30,"minLength":0}],"responses":{"200":{"description":"OK","schema":{"$ref":"#/definitions/GenreCollection"}},"400":{"description":"Bad Request","schema":{"$ref":"#/definitions/error"}}},"schemes":["http"]}},"/api/v2/genre/new":{"post":{"tags":["genre"],"summary":"create genre","description":"ジャンルの新規作成","operationId":"genre#create","produces":["application/vnd.goa.error"],"parameters":[{"name":"name","in":"query","description":"ジャンル名(1~30文字)","required":true,"type":"string","maxLength":30,"minLength":1}],"responses":{"201":{"description":"Created"},"400":{"description":"Bad Request","schema":{"$ref":"#/definitions/error"}}},"schemes":["http"]}},"/api/v2/user/{eventID}/keep":{"put":{"tags":["user"],"summary":"event fav update user","description":"イベントのお気に入り操作","operationId":"user#event fav update","produces":["application/vnd.goa.error"],"parameters":[{"name":"eventID","in":"path","description":"イベントID（連番）","required":true,"type":"integer"},{"name":"userID","in":"query","description":"ユーザーID（連番）","required":true,"type":"integer"}],"responses":{"204":{"description":"No Content"},"400":{"description":"Bad Request","schema":{"$ref":"#/definitions/error"}},"404":{"description":"Not Found"}},"schemes":["http"]}},"/api/v2/user/{eventID}/nokeep":{"put":{"tags":["user"],"summary":"event fav update user","description":"イベントのお気に入り操作","operationId":"user#event fav update#1","produces":["application/vnd.goa.error"],"parameters":[{"name":"eventID","in":"path","description":"イベントID（連番）","required":true,"type":"integer"},{"name":"userID","in":"query","description":"ユーザーID（連番）","required":true,"type":"integer"}],"responses":{"204":{"description":"No Content"},"400":{"description":"Bad Request","schema":{"$ref":"#/definitions/error"}},"404":{"description":"Not Found"}},"schemes":["http"]}},"/api/v2/user/{genreID}/add":{"put":{"tags":["user"],"summary":"genre fav update user","description":"ジャンルお気に入り操作","operationId":"user#genre fav update","produces":["application/vnd.goa.error"],"parameters":[{"name":"genreID","in":"path","description":"genreID（連番）","required":true,"type":"integer"},{"name":"userID","in":"query","description":"ユーザーID（連番）","required":true,"type":"integer"}],"responses":{"204":{"description":"No Content"},"400":{"description":"Bad Request","schema":{"$ref":"#/definitions/error"}},"404":{"description":"Not Found"}},"schemes":["http"]}},"/api/v2/user/{genreID}/remove":{"put":{"tags":["user"],"summary":"genre fav update user","description":"ジャンルお気に入り操作","operationId":"user#genre fav update#1","produces":["application/vnd.goa.error"],"parameters":[{"name":"genreID","in":"path","description":"genreID（連番）","required":true,"type":"integer"},{"name":"userID","in":"query","description":"ユーザーID（連番）","required":true,"type":"integer"}],"responses":{"204":{"description":"No Content"},"400":{"description":"Bad Request","schema":{"$ref":"#/definitions/error"}},"404":{"description":"Not Found"}},"schemes":["http"]}},"/swagger.json":{"get":{"summary":"Download public/swagger/swagger.json","operationId":"swagger#/swagger.json","responses":{"200":{"description":"File downloaded","schema":{"type":"file"}}},"schemes":["http"]}},"/swagger/{filepath}":{"get":{"summary":"Download swagger/dist","operationId":"swagger#/swagger/*filepath","parameters":[{"name":"filepath","in":"path","description":"Relative file path","required":true,"type":"string"}],"responses":{"200":{"description":"File downloaded","schema":{"type":"file"}},"404":{"description":"File not found","schema":{"$ref":"#/definitions/error"}}},"schemes":["http"]}}},"definitions":{"Event":{"title":"Mediatype identifier: application/vnd.event+json; view=default","type":"object","properties":{"ID":{"type":"integer","description":"ID","example":1,"format":"int64"},"accepted":{"type":"integer","description":"参加登録済み人数","example":10,"format":"int64"},"apiID":{"type":"string","description":"APIの種類 enum(ATDN=1,CONNPASS=2,DOORKEEPER=3)","example":"ATDN"},"endAt":{"type":"string","description":"終了日時","example":"2016-01-01 18:00:00"},"limit":{"type":"integer","description":"参加人数上限","example":10,"format":"int64"},"place":{"type":"string","description":"開催地","example":"東京都渋谷区3-31-205"},"startAt":{"type":"string","description":"開催日時","example":"2016-01-01 10:10:12"},"title":{"type":"string","description":"イベント名","example":"アジャイル開発勉強会"},"url":{"type":"string","description":"イベントページURL","example":"2016-01-01 10:10:12"},"waitlisted":{"type":"integer","description":"キャンセル待ち人数","example":5,"format":"int64"}},"description":"イベント情報 (default view)","example":{"ID":1,"accepted":10,"apiID":"ATDN","endAt":"2016-01-01 18:00:00","limit":10,"place":"東京都渋谷区3-31-205","startAt":"2016-01-01 10:10:12","title":"アジャイル開発勉強会","url":"2016-01-01 10:10:12","waitlisted":5},"required":["ID","apiID","title","url","limit","accepted","waitlisted","place","startAt"]},"EventCollection":{"title":"Mediatype identifier: application/vnd.event+json; type=collection; view=default","type":"array","items":{"$ref":"#/definitions/Event"},"description":"EventCollection is the media type for an array of Event (default view)","example":[{"ID":1,"accepted":10,"apiID":"ATDN","endAt":"2016-01-01 18:00:00","limit":10,"place":"東京都渋谷区3-31-205","startAt":"2016-01-01 10:10:12","title":"アジャイル開発勉強会","url":"2016-01-01 10:10:12","waitlisted":5},{"ID":1,"accepted":10,"apiID":"ATDN","endAt":"2016-01-01 18:00:00","limit":10,"place":"東京都渋谷区3-31-205","startAt":"2016-01-01 10:10:12","title":"アジャイル開発勉強会","url":"2016-01-01 10:10:12","waitlisted":5}]},"Genre":{"title":"Mediatype identifier: application/vnd.genre+json; view=default","type":"object","properties":{"ID":{"type":"integer","description":"ジャンルID","example":1,"format":"int64"},"name":{"type":"string","description":"ジャンル名","example":"javascript"}},"description":"ジャンル (default view)","example":{"ID":1,"name":"javascript"}},"GenreCollection":{"title":"Mediatype identifier: application/vnd.genre+json; type=collection; view=default","type":"array","items":{"$ref":"#/definitions/Genre"},"description":"GenreCollection is the media type for an array of Genre (default view)","example":[{"ID":1,"name":"javascript"}]},"error":{"title":"Mediatype identifier: application/vnd.goa.error; view=default","type":"object","properties":{"code":{"type":"string","description":"an application-specific error code, expressed as a string value.","example":"invalid_value"},"detail":{"type":"string","description":"a human-readable explanation specific to this occurrence of the problem.","example":"Value of ID must be an integer"},"id":{"type":"string","description":"a unique identifier for this particular occurrence of the problem.","example":"3F1FKVRR"},"meta":{"type":"object","description":"a meta object containing non-standard meta-information about the error.","example":{"timestamp":1458609066},"additionalProperties":true},"status":{"type":"string","description":"the HTTP status code applicable to this problem, expressed as a string value.","example":"400"}},"description":"Error response media type (default view)","example":{"code":"invalid_value","detail":"Value of ID must be an integer","id":"3F1FKVRR","meta":{"timestamp":1458609066},"status":"400"}}},"responses":{"Created":{"description":"Created"},"NoContent":{"description":"No Content"},"NotFound":{"description":"Not Found"}},"externalDocs":{"description":"eventory guide","url":"https://github.com/tikasan/eventory/wiki"}}